{
    "openapi": "3.0.0",
    "info": {
        "version": "",
        "title": "Cryptagio API",
        "description": "# Public & Private methods\n<table>\n  <thead>\n  <tr> \n    <td> <b>Public methods<\/b> <\/td>\n    <td> <b>Private methods<\/b> <\/td>\n  <\/tr>\n  <\/thead>\n  <tr> \n    <td> No authorization required <\/td>\n    <td> Authorization required <\/td>\n  <\/tr>\n<\/table>\n\n# Authorization\n\n  To use private methods, you need to get your access\/secret key first (on [cryptagio.com](https:\/\/cryptagio.com)). After signed up and verified, visit API Tokens page to get your keys. \n  <p> All requests to the private methods require these headers:\n<hr\/>\n  <table>\n  <tr> \n    <td> <b>X-Public-Key<\/b> <\/td>\n    <td> Your access key.<\/td>\n  <\/tr>\n  <tr> \n    <td> <b>X-Tonce<\/b> <\/td>\n    <td> Tonce is a timestamp in integer, stands for microseconds elapsed since Unix epoch. Tonce must be within 30 seconds of server's current time. Each tonce can only be used once.<\/td>\n  <\/tr>\n  <tr> \n    <td> <b>X-Signature<\/b> <\/td>\n    <td> Signature of the API request, generated by you, use your secret key.<\/td>\n  <\/tr>\n  <\/table>\n  ",
        "termsOfService": ""
    },
    "servers": [
        "https\/"
    ],
    "paths": {
        "\/info": {
            "get": {
                "summary": "Get Info",
                "description": "Get information..",
                "operationId": "GetInfo",
                "deprecated": 0,
                "parameters": []
            }
        },
        "\/ticker": {
            "get": {
                "summary": "Get Ticker",
                "description": "Get ticker of all markets..",
                "operationId": "GetTicker",
                "deprecated": 0,
                "parameters": []
            }
        },
        "\/trades": {
            "get": {
                "summary": "Get Trades",
                "description": "Get recent trades on market, each trade is included only once. Trades are sorted in reverse creation order.",
                "operationId": "GetTrades",
                "deprecated": 0,
                "parameters": [
                    {
                        "name": "limit",
                        "in": "query",
                        "description": "Limit the number of returned trades."
                    },
                    {
                        "name": "order",
                        "in": "query",
                        "description": "If set, returned orders will be sorted in specific order."
                    },
                    {
                        "name": "from_time",
                        "in": "query",
                        "description": "Filter trades by time. An integer represents the seconds elapsed since Unix epoch. If set, only data after that time will be returned."
                    },
                    {
                        "name": "to_time",
                        "in": "query",
                        "description": "Filter trades by time. An integer represents the seconds elapsed since Unix epoch. If set, only data before that time will be returned."
                    },
                    {
                        "name": "from_uuid",
                        "in": "query",
                        "description": "Filter trades by id. If set, only trades created after the trade will be returned."
                    },
                    {
                        "name": "market",
                        "in": "query",
                        "description": "Filter trades by market. It's always in the form of xxxyyy, where xxx is the base currency code, yyy is the quote currency code."
                    },
                    {
                        "name": "side",
                        "in": "query",
                        "description": ""
                    }
                ]
            }
        },
        "\/trades\/my": {
            "get": {
                "summary": "Get My Trades",
                "description": "Trades are sorted in reverse creation order.",
                "operationId": "GetTradesMy",
                "deprecated": 0,
                "parameters": [
                    {
                        "name": "limit",
                        "in": "query",
                        "description": "Limit the number of returned trades."
                    },
                    {
                        "name": "order",
                        "in": "query",
                        "description": "If set, returned orders will be sorted in specific order."
                    },
                    {
                        "name": "from_time",
                        "in": "query",
                        "description": "Filter trades by time. An integer represents the seconds elapsed since Unix epoch. If set, only data after that time will be returned."
                    },
                    {
                        "name": "to_time",
                        "in": "query",
                        "description": "Filter trades by time. An integer represents the seconds elapsed since Unix epoch. If set, only data before that time will be returned."
                    },
                    {
                        "name": "from_uuid",
                        "in": "query",
                        "description": "Filter trades by id. If set, only trades created after the trade will be returned."
                    },
                    {
                        "name": "market",
                        "in": "query",
                        "description": "Filter trades by market. It's always in the form of xxxyyy, where xxx is the base currency code, yyy is the quote currency code."
                    },
                    {
                        "name": "side",
                        "in": "query",
                        "description": ""
                    }
                ]
            }
        },
        "\/balances": {
            "get": {
                "summary": "Get Balances",
                "description": "Get user balances..",
                "operationId": "GetBalances",
                "deprecated": 0,
                "parameters": []
            }
        },
        "\/orders\/my": {
            "get": {
                "summary": "GetMy  Orders",
                "description": "Trades are sorted in reverse creation order.",
                "operationId": "GetOrdersMy",
                "deprecated": 0,
                "parameters": [
                    {
                        "name": "limit",
                        "in": "query",
                        "description": "Limit the number of returned trades."
                    },
                    {
                        "name": "order",
                        "in": "query",
                        "description": "If set, returned orders will be sorted in specific order."
                    },
                    {
                        "name": "from_time",
                        "in": "query",
                        "description": "Filter trades by time. An integer represents the seconds elapsed since Unix epoch. If set, only data after that time will be returned."
                    },
                    {
                        "name": "to_time",
                        "in": "query",
                        "description": "Filter trades by time. An integer represents the seconds elapsed since Unix epoch. If set, only data before that time will be returned."
                    },
                    {
                        "name": "from_uuid",
                        "in": "query",
                        "description": "Filter trades by id. If set, only trades created after the trade will be returned."
                    },
                    {
                        "name": "market",
                        "in": "query",
                        "description": "Filter trades by market. It's always in the form of xxxyyy, where xxx is the base currency code, yyy is the quote currency code."
                    },
                    {
                        "name": "side",
                        "in": "query",
                        "description": ""
                    },
                    {
                        "name": "type",
                        "in": "query",
                        "description": "Filter orders by type."
                    },
                    {
                        "name": "status",
                        "in": "query",
                        "description": "Filter orders by status."
                    }
                ]
            }
        },
        "\/orders": {
            "post": {
                "summary": "Post Orders",
                "description": "Accepts an array of JSON objects.",
                "operationId": "PostOrders",
                "deprecated": 0,
                "parameters": []
            }
        },
        "\/orders\/cancel": {
            "post": {
                "summary": "Post Orders Cancel",
                "description": "Accepts JSON object. Cancels all orders if no parameters are passed.",
                "operationId": "PostOrdersCancel",
                "deprecated": 0,
                "parameters": []
            }
        },
        "\/orders\/{uuid}": {
            "delete": {
                "summary": "Delete Orders",
                "description": "Cancel order by uuid..",
                "operationId": "DeleteOrdersUu",
                "deprecated": 0,
                "parameters": [
                    {
                        "name": "uuid",
                        "in": "path",
                        "description": ""
                    }
                ]
            }
        }
    },
    "components": {
        "schemas": []
    }
}